geolog/__init__.py
geolog/geolog.py
geolog-0.0.8.dist-info/LICENSE
geolog-0.0.8.dist-info/METADATA
geolog-0.0.8.dist-info/WHEEL
geolog-0.0.8.dist-info/dependency_links.txt
geolog-0.0.8.dist-info/top_level.txt
geolog-0.0.8.dist-info/RECORD
