Metadata-Version: 2.1
Name: geolog
Version: 0.0.8
Summary: My senior year GEOG 510 project.
Home-page: https://github.com/whitson-buck/geolog
Author: Whitson Buck
Author-email: whitsonbuck@gmail.com
License: MIT license
Keywords: geolog
Classifier: Development Status :: 2 - Pre-Alpha
Classifier: Intended Audience :: Developers
Classifier: License :: OSI Approved :: MIT License
Classifier: Natural Language :: English
Classifier: Programming Language :: Python :: 3
Classifier: Programming Language :: Python :: 3.7
Classifier: Programming Language :: Python :: 3.8
Classifier: Programming Language :: Python :: 3.9
Classifier: Programming Language :: Python :: 3.10
Requires-Python: >=3.7
License-File: LICENSE
Requires-Dist: ipyleaflet
Requires-Dist: folium
